confignest/__init__.py
confignest/src.py
confignest-1.0.5.dist-info/LICENSE
confignest-1.0.5.dist-info/METADATA
confignest-1.0.5.dist-info/WHEEL
confignest-1.0.5.dist-info/top_level.txt
confignest-1.0.5.dist-info/RECORD
