Metadata-Version: 2.1
Name: confignest
Version: 1.0.5
Summary: Managing Complex Configs in Nested Way.
Home-page: https://github.com/0-1CxH/ConfigNest
Author: github.com/0-1CxH
Author-email: h0.1c@foxmail.com
License: MIT Licence
Keywords: pip,confignest
Platform: any
License-File: LICENSE
